Metadata-Version: 2.1
Name: allcountry
Version: 0.1
Summary: all city in world
Home-page: https://github.com/SerhatYildrm/World
Author: Serhat YILDIRIM
Author-email: serhatylidrm0@gmail.com
License: UNKNOWN
Platform: UNKNOWN
Classifier: Programming Language :: Python :: 3
Classifier: License :: OSI Approved :: MIT License
Classifier: Operating System :: OS Independent
Requires-Python: >=3.6
